jenkinscli/__init__.py
jenkinscli/cli/__init__.py
jenkinscli/cli/cat.py
jenkinscli/cli/info.py
jenkinscli/cli/list.py
jenkinscli/cli/main.py
jenkinscli/cli/parser.py
jenkinscli/cli/ping.py
jenkinscli/cli/run.py
jenkinscli/test/__init__.py
jenkinscli/test/test_list.py
jenkinscli/test/test_run.py
jenkinscli-0.1.dev0.data/scripts/jenkins
jenkinscli-0.1.dev0.dist-info/DESCRIPTION.rst
jenkinscli-0.1.dev0.dist-info/METADATA
jenkinscli-0.1.dev0.dist-info/metadata.json
jenkinscli-0.1.dev0.dist-info/RECORD
jenkinscli-0.1.dev0.dist-info/top_level.txt
jenkinscli-0.1.dev0.dist-info/WHEEL
