Metadata-Version: 2.0
Name: jenkinscli
Version: 0.1.dev0
Summary: Simple Jenkins CLI
Home-page: UNKNOWN
Author: Bernardo Vale
Author-email: UNKNOWN
License: Apache License 2.0
Platform: UNKNOWN
Classifier: Development Status :: 4 - Beta
Classifier: Environment :: Console
Classifier: Intended Audience :: Developers
Classifier: License :: OSI Approved :: Apache Software License
Classifier: Programming Language :: Python :: 3
Classifier: Programming Language :: Python :: 3.6
Requires-Dist: python-jenkins (==0.4.14)
Requires-Dist: pytz (==2017.2)
Requires-Dist: requests (==2.13.0)
Requires-Dist: six (==1.10.0)
